.coveragerc
.gitignore
CMakeLists.txt
LICENSE
MANIFEST.in
README.md
setup.cfg
setup.py
.github/workflows/building-conda.yml
.github/workflows/building.yml
.github/workflows/linting.yml
.github/workflows/stale.yml
.github/workflows/testing.yml
.github/workflows/cuda/cu101-Linux-env.sh
.github/workflows/cuda/cu101-Linux.sh
.github/workflows/cuda/cu101-Windows-env.sh
.github/workflows/cuda/cu101-Windows.sh
.github/workflows/cuda/cu102-Linux-env.sh
.github/workflows/cuda/cu102-Linux.sh
.github/workflows/cuda/cu102-Windows-env.sh
.github/workflows/cuda/cu102-Windows.sh
.github/workflows/cuda/cu111-Linux-env.sh
.github/workflows/cuda/cu111-Linux.sh
.github/workflows/cuda/cu111-Windows-env.sh
.github/workflows/cuda/cu111-Windows.sh
.github/workflows/cuda/cu113-Linux-env.sh
.github/workflows/cuda/cu113-Linux.sh
.github/workflows/cuda/cu113-Windows-env.sh
.github/workflows/cuda/cu113-Windows.sh
.github/workflows/cuda/cu115-Linux-env.sh
.github/workflows/cuda/cu115-Linux.sh
.github/workflows/cuda/cu115-Windows-env.sh
.github/workflows/cuda/cu115-Windows.sh
.github/workflows/cuda/cu116-Linux-env.sh
.github/workflows/cuda/cu116-Linux.sh
.github/workflows/cuda/cu116-Windows-env.sh
.github/workflows/cuda/cu116-Windows.sh
.github/workflows/cuda/cu117-Linux-env.sh
.github/workflows/cuda/cu117-Linux.sh
.github/workflows/cuda/cu117-Windows-env.sh
.github/workflows/cuda/cu117-Windows.sh
.github/workflows/cuda/cu118-Linux-env.sh
.github/workflows/cuda/cu118-Linux.sh
.github/workflows/cuda/cu118-Windows-env.sh
.github/workflows/cuda/cu118-Windows.sh
.github/workflows/cuda/cu121-Linux-env.sh
.github/workflows/cuda/cu121-Linux.sh
.github/workflows/cuda/cu121-Windows-env.sh
.github/workflows/cuda/cu121-Windows.sh
cmake/TorchClusterConfig.cmake.in
conda/pytorch-cluster/README.md
conda/pytorch-cluster/build_conda.sh
conda/pytorch-cluster/meta.yaml
csrc/cluster.h
csrc/extensions.h
csrc/fps.cpp
csrc/graclus.cpp
csrc/grid.cpp
csrc/knn.cpp
csrc/macros.h
csrc/nearest.cpp
csrc/radius.cpp
torch_cluster.egg-info/PKG-INFO
torch_cluster.egg-info/SOURCES.txt
torch_cluster.egg-info/dependency_links.txt
torch_cluster.egg-info/requires.txt
torch_cluster.egg-info/top_level.txt